jinjafx/__init__.py
jinjafx/__main__.py
jinjafx/jinjafx.py
jinjafx/extensions/ext_ansible_core.py
jinjafx/extensions/ext_ansible_netcommon.py
jinjafx/extensions/ext_jinjafx.py
jinjafx-1.27.3.dist-info/licenses/LICENSE
jinjafx-1.27.3.dist-info/METADATA
jinjafx-1.27.3.dist-info/WHEEL
jinjafx-1.27.3.dist-info/entry_points.txt
jinjafx-1.27.3.dist-info/top_level.txt
jinjafx-1.27.3.dist-info/RECORD
