Metadata-Version: 2.4
Name: jinjafx
Version: 1.27.3
Summary: JinjaFx - Jinja2 Templating Tool
Author-email: Chris Mason <chris@netnix.org>
License-Expression: MIT
Project-URL: Repository, https://github.com/cmason3/jinjafx.git
Project-URL: Issues, https://github.com/cmason3/jinjafx/issues
Project-URL: Changelog, https://github.com/cmason3/jinjafx/blob/main/CHANGELOG.md
Classifier: Development Status :: 5 - Production/Stable
Classifier: Programming Language :: Python :: 3
Requires-Python: >=3.10
License-File: LICENSE
Requires-Dist: jinja2>=3.0
Requires-Dist: pyyaml
Requires-Dist: cryptography>=3.1
Requires-Dist: netaddr
Requires-Dist: jsonschema
Dynamic: license-file
